spectra_assure_api_client/__init__.py
spectra_assure_api_client/py.typed
spectra_assure_api_client/spectra_assure_api_operations.py
spectra_assure_api_client/version.py
spectra_assure_api_client/communication/__init__.py
spectra_assure_api_client/communication/api.py
spectra_assure_api_client/communication/core.py
spectra_assure_api_client/communication/delete.py
spectra_assure_api_client/communication/download_criteria.py
spectra_assure_api_client/communication/downloader.py
spectra_assure_api_client/communication/downloader_exceptions.py
spectra_assure_api_client/communication/exceptions.py
spectra_assure_api_client/communication/get.py
spectra_assure_api_client/communication/patch.py
spectra_assure_api_client/communication/post.py
spectra_assure_api_client/communication/put.py
spectra_assure_api_client/operations/__init__.py
spectra_assure_api_client/operations/approve.py
spectra_assure_api_client/operations/base.py
spectra_assure_api_client/operations/checks.py
spectra_assure_api_client/operations/community_find_packages.py
spectra_assure_api_client/operations/community_report_package.py
spectra_assure_api_client/operations/community_report_version.py
spectra_assure_api_client/operations/create.py
spectra_assure_api_client/operations/delete.py
spectra_assure_api_client/operations/download.py
spectra_assure_api_client/operations/edit.py
spectra_assure_api_client/operations/list.py
spectra_assure_api_client/operations/listGroups.py
spectra_assure_api_client/operations/reject.py
spectra_assure_api_client/operations/report.py
spectra_assure_api_client/operations/revoke.py
spectra_assure_api_client/operations/rl_safe.py
spectra_assure_api_client/operations/scan.py
spectra_assure_api_client/operations/status.py
spectra_assure_api_client/operations/sync.py
spectra_assure_api_client/operations/url_import.py
spectra_assure_api_client/operations/usage.py
spectra_assure_sdk-1.0.10.dist-info/METADATA
spectra_assure_sdk-1.0.10.dist-info/WHEEL
spectra_assure_sdk-1.0.10.dist-info/licenses/LICENSE
spectra_assure_sdk-1.0.10.dist-info/RECORD
