Metadata-Version: 2.4
Name: spectra-assure-sdk
Version: 1.0.10
Summary: Python package for interfacing with the Spectra Assure Portal API.
Project-URL: Bug Tracker, https://github.com/reversinglabs/spectra-assure-sdk/issues
Project-URL: Home Page, https://github.com/reversinglabs/spectra-assure-sdk/
Project-URL: Repository, https://github.com/reversinglabs/spectra-assure-sdk/
Author: ReversingLabs
Maintainer-email: ReversingLabs <support@reversinglabs.com>
License-Expression: MIT
License-File: LICENSE
Keywords: Python,ReversingLabs,Secure Software,Spectra Assure
Classifier: Environment :: Console
Classifier: Intended Audience :: Developers
Classifier: License :: OSI Approved :: MIT License
Classifier: Operating System :: OS Independent
Classifier: Programming Language :: Python :: 3
Classifier: Topic :: Internet
Classifier: Topic :: Software Development :: Libraries :: Python Modules
Requires-Python: >=3.10
Requires-Dist: requests==2.32.5
